phones_local/__init__.py
phones_local/phone_local_constans.py
phones_local/phones_local.py
phones_local-0.0.43.dist-info/METADATA
phones_local-0.0.43.dist-info/WHEEL
phones_local-0.0.43.dist-info/top_level.txt
phones_local-0.0.43.dist-info/RECORD
